bazaar_dl/__init__.py
bazaar_dl/bazaar_dl.py
Bazaar_Dl-1.0.3.dist-info/LICENSE
Bazaar_Dl-1.0.3.dist-info/METADATA
Bazaar_Dl-1.0.3.dist-info/WHEEL
Bazaar_Dl-1.0.3.dist-info/top_level.txt
Bazaar_Dl-1.0.3.dist-info/RECORD
