Metadata-Version: 2.1
Name: Bazaar-Dl
Version: 1.0.3
Summary: Simple Python package for directly downloading applications from Cafe Bazaar.
Author: Matin Baloochestani (Matin-B)
Author-email: MatiinBaloochestani@Gmail.com
Keywords: python,bazaar_dl,bazaar-dl,Cafe-Bazaar
Classifier: Development Status :: 1 - Planning
Classifier: Intended Audience :: Developers
Classifier: Programming Language :: Python :: 3
Classifier: Operating System :: Unix
Classifier: Operating System :: MacOS :: MacOS X
Classifier: Operating System :: Microsoft :: Windows
License-File: LICENSE
Requires-Dist: requests
